{"nodes": [{"id": "d_dev_notas_zincao_app_components_header_headerdropmenu_vue", "label": "HeaderDropmenu.vue", "file_type": "code", "source_file": "D:\\dev\\notas-zincao\\app\\components\\header\\HeaderDropmenu.vue", "source_location": "L1"}, {"id": "header_headerdropmenu_fechar", "label": "fechar()", "file_type": "code", "source_file": "D:\\dev\\notas-zincao\\app\\components\\header\\HeaderDropmenu.vue", "source_location": "L19"}, {"id": "header_headerdropmenu_toggle", "label": "toggle()", "file_type": "code", "source_file": "D:\\dev\\notas-zincao\\app\\components\\header\\HeaderDropmenu.vue", "source_location": "L23"}, {"id": "header_headerdropmenu_handledocumentclick", "label": "handleDocumentClick()", "file_type": "code", "source_file": "D:\\dev\\notas-zincao\\app\\components\\header\\HeaderDropmenu.vue", "source_location": "L27"}, {"id": "header_headerdropmenu_handleesc", "label": "handleEsc()", "file_type": "code", "source_file": "D:\\dev\\notas-zincao\\app\\components\\header\\HeaderDropmenu.vue", "source_location": "L38"}], "edges": [{"source": "d_dev_notas_zincao_app_components_header_headerdropmenu_vue", "target": "header_headerdropmenu_fechar", "relation": "contains", "confidence": "EXTRACTED", "source_file": "D:\\dev\\notas-zincao\\app\\components\\header\\HeaderDropmenu.vue", "source_location": "L19", "weight": 1.0}, {"source": "d_dev_notas_zincao_app_components_header_headerdropmenu_vue", "target": "header_headerdropmenu_toggle", "relation": "contains", "confidence": "EXTRACTED", "source_file": "D:\\dev\\notas-zincao\\app\\components\\header\\HeaderDropmenu.vue", "source_location": "L23", "weight": 1.0}, {"source": "d_dev_notas_zincao_app_components_header_headerdropmenu_vue", "target": "header_headerdropmenu_handledocumentclick", "relation": "contains", "confidence": "EXTRACTED", "source_file": "D:\\dev\\notas-zincao\\app\\components\\header\\HeaderDropmenu.vue", "source_location": "L27", "weight": 1.0}, {"source": "d_dev_notas_zincao_app_components_header_headerdropmenu_vue", "target": "header_headerdropmenu_handleesc", "relation": "contains", "confidence": "EXTRACTED", "source_file": "D:\\dev\\notas-zincao\\app\\components\\header\\HeaderDropmenu.vue", "source_location": "L38", "weight": 1.0}, {"source": "header_headerdropmenu_handledocumentclick", "target": "header_headerdropmenu_fechar", "relation": "calls", "context": "call", "confidence": "EXTRACTED", "source_file": "D:\\dev\\notas-zincao\\app\\components\\header\\HeaderDropmenu.vue", "source_location": "L34", "weight": 1.0}, {"source": "header_headerdropmenu_handleesc", "target": "header_headerdropmenu_fechar", "relation": "calls", "context": "call", "confidence": "EXTRACTED", "source_file": "D:\\dev\\notas-zincao\\app\\components\\header\\HeaderDropmenu.vue", "source_location": "L40", "weight": 1.0}], "raw_calls": [{"caller_nid": "header_headerdropmenu_handledocumentclick", "callee": "contains", "is_member_call": true, "source_file": "D:\\dev\\notas-zincao\\app\\components\\header\\HeaderDropmenu.vue", "source_location": "L33"}]}